decanter/__init__.py
decanter/core/__init__.py
decanter/core/client.py
decanter/core/context.py
decanter/core/plot.py
decanter/core/core_api/__init__.py
decanter/core/core_api/api.py
decanter/core/core_api/body_obj.py
decanter/core/core_api/model.py
decanter/core/core_api/predict_input.py
decanter/core/core_api/setup_input.py
decanter/core/core_api/train_input.py
decanter/core/core_api/worker.py
decanter/core/enums/__init__.py
decanter/core/enums/algorithms.py
decanter/core/enums/categorical_group_by_method.py
decanter/core/enums/evaluators.py
decanter/core/enums/numerical_group_by_methods.py
decanter/core/enums/time_units.py
decanter/core/extra/__init__.py
decanter/core/extra/const.py
decanter/core/extra/decorators.py
decanter/core/extra/utils.py
decanter/core/jobs/__init__.py
decanter/core/jobs/data_setup.py
decanter/core/jobs/data_upload.py
decanter/core/jobs/experiment.py
decanter/core/jobs/job.py
decanter/core/jobs/predict_result.py
decanter/core/jobs/task.py
decanter_ai_core_sdk-1.1.11.dist-info/LICENSE
decanter_ai_core_sdk-1.1.11.dist-info/METADATA
decanter_ai_core_sdk-1.1.11.dist-info/WHEEL
decanter_ai_core_sdk-1.1.11.dist-info/top_level.txt
decanter_ai_core_sdk-1.1.11.dist-info/RECORD
