Metadata-Version: 2.1
Name: decanter-ai-core-sdk
Version: 1.1.11
Summary: Decanter AI Core SDK for the easy use of Decanter Core API.
Home-page: https://github.com/MoBagel/decanter-ai-core-sdk
Author: Mobagel
Author-email: us@mobagel.com
License: MIT
Classifier: Programming Language :: Python :: 3
Classifier: License :: OSI Approved :: MIT License
Classifier: Operating System :: OS Independent
Requires-Python: >=3.7
License-File: LICENSE
Requires-Dist: requests (>=2.25.1)
Requires-Dist: requests-toolbelt (>=0.9.1)
Requires-Dist: pandas (>=1.3.0)
Requires-Dist: matplotlib (>=3.4.2)
Requires-Dist: tqdm (>=4.61.2)
Requires-Dist: numpy (>=1.21.0)
Provides-Extra: dev
Requires-Dist: twine ; extra == 'dev'
Requires-Dist: tox ; extra == 'dev'
Requires-Dist: pytest ; extra == 'dev'
Requires-Dist: responses ; extra == 'dev'
Requires-Dist: flake8 ; extra == 'dev'
Requires-Dist: pylint-quotes ; extra == 'dev'
